xltemplate/__init__.py
xltemplate/py.typed
xltemplate/schema.py
xltemplate/sheet.py
xltemplate/utils.py
xltemplate/workbook.py
xltemplate-0.2.0.dist-info/METADATA
xltemplate-0.2.0.dist-info/WHEEL
xltemplate-0.2.0.dist-info/top_level.txt
xltemplate-0.2.0.dist-info/RECORD
