Metadata-Version: 2.4
Name: xltemplate
Version: 0.2.0
Summary: A clean OOP interface for populating Excel templates with DataFrames
Author: G. Lance Couzens
License: MIT
Project-URL: Homepage, https://github.com/mostlyunoriginal/xltemplate
Project-URL: Documentation, https://mostlyunoriginal.github.io/xltemplate/
Project-URL: Repository, https://github.com/mostlyunoriginal/xltemplate
Keywords: excel,xlsx,template,pandas,polars,dataframe
Classifier: Development Status :: 3 - Alpha
Classifier: Intended Audience :: Developers
Classifier: License :: OSI Approved :: MIT License
Classifier: Programming Language :: Python :: 3
Classifier: Programming Language :: Python :: 3.10
Classifier: Programming Language :: Python :: 3.11
Classifier: Programming Language :: Python :: 3.12
Classifier: Topic :: Office/Business :: Office Suites
Requires-Python: >=3.10
Requires-Dist: openpyxl>=3.1.0
Provides-Extra: pandas
Requires-Dist: pandas>=2.0.0; extra == "pandas"
Provides-Extra: polars
Requires-Dist: polars>=0.20.0; extra == "polars"
Provides-Extra: all
Requires-Dist: pandas>=2.0.0; extra == "all"
Requires-Dist: polars>=0.20.0; extra == "all"
Provides-Extra: dev
Requires-Dist: pytest>=7.0.0; extra == "dev"
Requires-Dist: pandas>=2.0.0; extra == "dev"
Requires-Dist: polars>=0.20.0; extra == "dev"
Provides-Extra: docs
Requires-Dist: mkdocs>=1.5.0; extra == "docs"
Requires-Dist: mkdocs-material>=9.0.0; extra == "docs"
Requires-Dist: mkdocstrings[python]>=0.24.0; extra == "docs"
